spil/__init__.py
spil/conf/__init__.py
spil/conf/configio.py
spil/conf/data_conf_load.py
spil/conf/global_conf.py
spil/conf/sid_conf_load.py
spil/conf/util.py
spil/sid/__init__.py
spil/sid/sid.py
spil/sid/core/__init__.py
spil/sid/core/query_helper.py
spil/sid/core/sid_factory.py
spil/sid/core/sid_resolver.py
spil/sid/core/utils.py
spil/sid/pathops/__init__.py
spil/sid/pathops/find_paths.py
spil/sid/pathops/fs_resolver.py
spil/sid/pathops/getter_paths.py
spil/sid/pathops/pathconfig.py
spil/sid/pathops/write_paths.py
spil/sid/read/__init__.py
spil/sid/read/finder.py
spil/sid/read/getter.py
spil/sid/read/tools.py
spil/sid/read/util.py
spil/sid/read/finders/__init__.py
spil/sid/read/finders/find_all.py
spil/sid/read/finders/find_cache.py
spil/sid/read/finders/find_constants.py
spil/sid/read/finders/find_glob.py
spil/sid/read/finders/find_list.py
spil/sid/read/getters/__init__.py
spil/sid/read/getters/getter_all.py
spil/sid/read/getters/getter_finder.py
spil/sid/read/unfolders/__init__.py
spil/sid/read/unfolders/expand.py
spil/sid/read/unfolders/extensions.py
spil/sid/read/unfolders/extrapolate.py
spil/sid/read/unfolders/or_op.py
spil/sid/read/unfolders/typed_narrow.py
spil/sid/write/__init__.py
spil/sid/write/write_all.py
spil/sid/write/writer.py
spil/tests/__init__.py
spil/tests/config_checks/__init__.py
spil/tests/config_checks/check_01_sid_config.py
spil/tests/config_checks/check_02_path_config.py
spil/tests/config_checks/check_03_config_coverage.py
spil/tests/feature_tests/__init__.py
spil/tests/feature_tests/test_lru.py
spil/tests/prep/__init__.py
spil/tests/prep/build_searches.py
spil/tests/prep/make_mock_fs.py
spil/tests/prep/parse_sids_from_fs.py
spil/tests/prep/save_sid_list_to_file.py
spil/tests/utils/__init__.py
spil/tests/utils/dualsearch_ab_tester.py
spil/tests/utils/search_tester.py
spil/tests/utils/sid_core_tester.py
spil/tests/utils/sid_data_tester.py
spil/tests/utils/sid_full_tester.py
spil/tests/utils/sid_path_tester.py
spil/util/__init__.py
spil-0.2.1.dist-info/METADATA
spil-0.2.1.dist-info/WHEEL
spil-0.2.1.dist-info/licenses/LICENSE
spil-0.2.1.dist-info/RECORD
