Metadata-Version: 2.1
Name: spil
Version: 0.2.1
Summary: The Simple Pipeline Lib.
Project-URL: Homepage, https://github.com/MichaelHaussmann/spil
Project-URL: Documentation, https://spil.readthedocs.io
Author-email: Michael Haussmann <spil@xeo.info>
License:                    GNU LESSER GENERAL PUBLIC LICENSE
License-File: LICENSE
Keywords: cg,cg-pipeline,path templates,vfx,vfx-pipeline
Classifier: Development Status :: 4 - Beta
Classifier: Intended Audience :: Developers
Classifier: License :: OSI Approved :: GNU Lesser General Public License v3 or later (LGPLv3+)
Classifier: Natural Language :: English
Classifier: Operating System :: OS Independent
Classifier: Programming Language :: Python
Classifier: Programming Language :: Python :: 3
Classifier: Programming Language :: Python :: 3.7
Classifier: Topic :: Software Development
Classifier: Topic :: Software Development :: Libraries
Requires-Python: >=3.7
Requires-Dist: codetiming
Requires-Dist: fileseq
Requires-Dist: future
Requires-Dist: logzero
Requires-Dist: resolva
Requires-Dist: typing-extensions
Provides-Extra: dev
Requires-Dist: pytest; extra == 'dev'
Provides-Extra: qc
Requires-Dist: black; extra == 'qc'
Requires-Dist: flake8; extra == 'qc'
Requires-Dist: isort; extra == 'qc'
Requires-Dist: mypy; extra == 'qc'
Requires-Dist: refurb; extra == 'qc'
Provides-Extra: sg
Requires-Dist: shotgun-api3; extra == 'sg'
Requires-Dist: unidecode; extra == 'sg'
